kiwi_keg/__init__.py
kiwi_keg/annotated_mapping.py
kiwi_keg/dict_utils.py
kiwi_keg/exceptions.py
kiwi_keg/file_utils.py
kiwi_keg/generator.py
kiwi_keg/image_definition.py
kiwi_keg/image_schema.py
kiwi_keg/keg.py
kiwi_keg/kiwi_description.py
kiwi_keg/logger.py
kiwi_keg/logger_filter.py
kiwi_keg/script_utils.py
kiwi_keg/source_info_generator.py
kiwi_keg/version.py
kiwi_keg/tools/__init__.py
kiwi_keg/tools/compose_kiwi_description.py
kiwi_keg/tools/generate_recipes_changelog.py
kiwi_keg-2.1.1.dist-info/LICENSE
kiwi_keg-2.1.1.dist-info/METADATA
kiwi_keg-2.1.1.dist-info/WHEEL
kiwi_keg-2.1.1.dist-info/entry_points.txt
kiwi_keg-2.1.1.dist-info/top_level.txt
kiwi_keg-2.1.1.dist-info/RECORD
