Metadata-Version: 2.1
Name: kiwi-keg
Version: 2.1.1
Summary: KEG - Image Composition Tool
Home-page: https://github.com/SUSE-Enceladus/keg
Download-URL: https://download.opensuse.org
Author: Public Cloud Team
Author-email: public-cloud-dev@susecloud.net
License: GPLv3+
Classifier: Development Status :: 5 - Production/Stable
Classifier: Intended Audience :: Developers
Classifier: License :: OSI Approved :: GNU General Public License v3 or later (GPLv3+)
Classifier: Operating System :: POSIX :: Linux
Classifier: Programming Language :: Python :: 3.6
Classifier: Programming Language :: Python :: 3.8
Classifier: Programming Language :: Python :: 3.10
Classifier: Topic :: System :: Operating System
License-File: LICENSE
Requires-Dist: docopt
Requires-Dist: Jinja2
Requires-Dist: kiwi (>=9.21.21)
Requires-Dist: PyYAML
Requires-Dist: schema
Requires-Dist: iso8601 ; python_version < "3.7.0"
